<?xml version="1.0" encoding="UTF-8"?>
<objects serializationModel="Studio.02.02.00">
	<object class="AudioFile" id="{63008672-3f70-4db4-adcb-3eb1b2577f0c}">
		<property name="assetPath">
			<value>Foxcat/Weapons/Micro Missiles/launch/GUNArtl-SCIFI_Micro Missiles Launch 07_LUBA_SOL DRIFT_GDC BUILD.wav</value>
		</property>
		<property name="frequencyInKHz">
			<value>48</value>
		</property>
		<property name="channelCount">
			<value>1</value>
		</property>
		<property name="length">
			<value>2.2440625000000001</value>
		</property>
		<relationship name="masterAssetFolder">
			<destination>{b88b94f9-c11e-4d97-932c-1b1bdf3e4d5e}</destination>
		</relationship>
	</object>
</objects>
